mdgo/__init__.py
mdgo/conductivity.py
mdgo/coordination.py
mdgo/core.py
mdgo/forcefield.py
mdgo/mdgopackmol.py
mdgo/msd.py
mdgo/residence_time.py
mdgo/util.py
mdgo/volume.py
tests/__init__.py
tests/test_conductivity.py
tests/test_coordination.py
tests/test_core.py
tests/test_forcefield.py
tests/test_mdgopackmol.py
tests/test_msd.py
tests/test_residence_time.py
tests/test_util.py
tests/test_volume.py
mdgo-0.2.4.dist-info/LICENSE.rst
mdgo-0.2.4.dist-info/METADATA
mdgo-0.2.4.dist-info/WHEEL
mdgo-0.2.4.dist-info/top_level.txt
mdgo-0.2.4.dist-info/RECORD
