Metadata-Version: 2.1
Name: mdgo
Version: 0.2.4
Summary: A codebase for MD simulation setup and results analysis.
Home-page: https://github.com/HT-MD/mdgo
Author: mdgo development team
Author-email: tingzheng_hou@berkeley.edu
Maintainer: Tingzheng Hou
Maintainer-email: tingzheng_hou@berkeley.edu
License: MIT
Keywords: LAMMPS,Gromacs,Molecular dynamics,liquid,charge,materials,science,solvation,diffusion,transport,conductivity,force field
Platform: UNKNOWN
Classifier: Programming Language :: Python :: 3
Classifier: Programming Language :: Python :: 3.7
Classifier: Programming Language :: Python :: 3.8
Classifier: Programming Language :: Python :: 3.9
Classifier: Development Status :: 3 - Alpha
Classifier: Intended Audience :: Science/Research
Classifier: License :: OSI Approved :: MIT License
Classifier: Operating System :: OS Independent
Classifier: Topic :: Scientific/Engineering :: Information Analysis
Classifier: Topic :: Scientific/Engineering :: Physics
Classifier: Topic :: Scientific/Engineering :: Chemistry
Classifier: Topic :: Software Development :: Libraries :: Python Modules
Requires-Python: >=3.7
Requires-Dist: numpy (>=1.16.0)
Requires-Dist: pandas
Requires-Dist: matplotlib
Requires-Dist: scipy
Requires-Dist: tqdm
Requires-Dist: pymatgen (>=2022.0.17)
Requires-Dist: statsmodels
Requires-Dist: pubchempy
Requires-Dist: MDAnalysis
Requires-Dist: selenium
Requires-Dist: typing-extensions
Provides-Extra: web
Requires-Dist: sphinx ; extra == 'web'
Requires-Dist: sphinx-rtd-theme ; extra == 'web'
Requires-Dist: sphinx-autodoc-typehints ; extra == 'web'
